{"digest":"f43b342a2e27da2708a94bde417a630e7ffeb1a5","css":"/*\n * Your Stylesheet\n *\n * This stylesheet is loaded when Atom starts up and is reloaded automatically\n * when it is changed.\n *\n * If you are unfamiliar with LESS, you can read more about it here:\n * http://www.lesscss.org\n */\n.tree-view {\n  font-size: 15px;\n}\n","imports":[{"path":"static/variables/ui-variables.less","digest":"a62842e88e9f6f18817f0a1662302588958b59ac"},{"path":"static/variables/syntax-variables.less","digest":"dbb8bc25cbfa6ac53763293d81b25b8d718230f9"}],"version":1}